auto_pypi/__init__.py
auto_pypi/auto_pypi.py
auto_pypi-2.2.2.dist-info/LICENSE
auto_pypi-2.2.2.dist-info/METADATA
auto_pypi-2.2.2.dist-info/WHEEL
auto_pypi-2.2.2.dist-info/entry_points.txt
auto_pypi-2.2.2.dist-info/top_level.txt
auto_pypi-2.2.2.dist-info/RECORD
