Metadata-Version: 2.1
Name: auto-pypi
Version: 2.2.2
Summary: A Python command line tool to automatically setup and upload your package to PyPi. 
Home-page: https://github.com/Listen180/auto_pypi
Author: Sen LEI
Author-email: sen.lei@outlook.com
License: BSD 3-clause
Keywords: python,package,pypi,shell
Platform: UNKNOWN
Classifier: Development Status :: 3 - Alpha
Classifier: Programming Language :: Python :: 3.8
Classifier: License :: OSI Approved :: BSD License
Classifier: Operating System :: OS Independent
License-File: LICENSE
Requires-Dist: click
